trivium/__init__.py
trivium/config.py
trivium/logger.py
trivium/api/__init__.py
trivium/api/_abc_rest_obj.py
trivium/api/api.py
trivium/api/rest_branch.py
trivium/api/rest_element.py
trivium/api/rest_organization.py
trivium/api/rest_project.py
trivium/api/rest_user.py
trivium/cli/__init__.py
trivium/cli/_command.py
trivium/cli/_subcommand_runner.py
trivium/cli/configure.py
trivium/cli/generate.py
trivium/cli/query.py
trivium/cli/transform.py
trivium/cli/version.py
trivium/cli/whoami.py
trivium/egesters/__init__.py
trivium/egesters/api_egester.py
trivium/egesters/json_egester.py
trivium/egesters/yaml_egester.py
trivium/ingesters/__init__.py
trivium/ingesters/json_ingester.py
trivium/ingesters/yaml_ingester.py
trivium/util/__init__.py
trivium/util/jmi.py
trivium_cli-0.2.0.data/scripts/trivium
trivium_cli-0.2.0.dist-info/LICENSE
trivium_cli-0.2.0.dist-info/METADATA
trivium_cli-0.2.0.dist-info/WHEEL
trivium_cli-0.2.0.dist-info/top_level.txt
trivium_cli-0.2.0.dist-info/RECORD
