Metadata-Version: 2.1
Name: trivium-cli
Version: 0.2.0
Summary: Trivium CLI
Home-page: https://triple.engineering
Author: Triple Dot Engineering
Author-email: pypi@triple.engineer
License: MIT
Platform: UNKNOWN
Requires-Python: >=3.6
License-File: LICENSE
Requires-Dist: python-docx (==0.8.11)
Requires-Dist: pandas
Requires-Dist: pylint
Requires-Dist: requests
Requires-Dist: pyyaml
